src/Lists.py
src/Processing.py
src/Time.py
src/__init__.py
src/import and test.py
datascience_workbench-0.0.3.dist-info/METADATA
datascience_workbench-0.0.3.dist-info/WHEEL
datascience_workbench-0.0.3.dist-info/license.md
datascience_workbench-0.0.3.dist-info/top_level.txt
datascience_workbench-0.0.3.dist-info/RECORD
