Metadata-Version: 2.1
Name: datascience-workbench
Version: 0.0.3
Summary: Utilities for data science projects
Home-page: UNKNOWN
Author: Philipp Schmalen
Author-email: philippschmalen@gmail.com
License: UNKNOWN
Platform: UNKNOWN
